bamurai/VERSION
bamurai/__init__.py
bamurai/assign_samples.py
bamurai/chunk.py
bamurai/cli.py
bamurai/core.py
bamurai/divide.py
bamurai/extract_sample.py
bamurai/get_hto.py
bamurai/logging_config.py
bamurai/split.py
bamurai/split_samples.py
bamurai/stats.py
bamurai/utils.py
bamurai/utils_samples.py
bamurai/validate.py
bamurai/version.py
bamurai-0.10.0.dist-info/licenses/LICENSE
tests/__init__.py
tests/test_core.py
bamurai-0.10.0.dist-info/METADATA
bamurai-0.10.0.dist-info/WHEEL
bamurai-0.10.0.dist-info/entry_points.txt
bamurai-0.10.0.dist-info/top_level.txt
bamurai-0.10.0.dist-info/RECORD
