Metadata-Version: 2.4
Name: bamurai
Version: 0.10.0
Summary: A package for splitting reads in BAM/FASTQ files into smaller fragments.
Author: Shian Su
License: Apache-2.0
License-File: LICENSE
Requires-Dist: pysam
Requires-Dist: numpy
Requires-Dist: pandas
Provides-Extra: dev
Requires-Dist: pytest; extra == "dev"
Requires-Dist: black; extra == "dev"
Requires-Dist: mypy; extra == "dev"
Dynamic: license-file
